bisslog_supabase/__init__.py
bisslog_supabase/basic_helper.py
bisslog_supabase/exception_handler.py
bisslog_supabase-0.0.0.dist-info/licenses/LICENSE
bisslog_supabase-0.0.0.dist-info/METADATA
bisslog_supabase-0.0.0.dist-info/WHEEL
bisslog_supabase-0.0.0.dist-info/top_level.txt
bisslog_supabase-0.0.0.dist-info/RECORD
