Metadata-Version: 2.4
Name: bisslog_supabase
Version: 0.0.0
Summary: It is an extension of the bisslog library to support processes with the Supabase service using the official Python SDK.
Author-email: Darwin Stiven Herrera Cartagena <darwinsherrerac@gmail.com>
Project-URL: Homepage, https://github.com/darwinhc/bisslog-supabase-py
Keywords: hexagonal,adapters,supabase
Classifier: Programming Language :: Python :: 3
Classifier: Operating System :: OS Independent
Requires-Python: >=3.7
License-File: LICENSE
Requires-Dist: supabase
Requires-Dist: httpx
Requires-Dist: bisslog>=0.0.7
Dynamic: license-file
